{
    "status": "OK",
    "data": {
        "persistentUrl": "https://hdl.handle.net/1902.29/CAPS-ELECT",
        "publisher": "UNC Dataverse",
        "publicationDate": "2009-05-18",
        "datasetVersion": {
            "id": 3432,
            "storageIdentifier": "file://1902.29/CAPS-ELECT",
            "versionNumber": 1,
            "versionMinorNumber": 0,
            "versionState": "RELEASED",
            "versionNote": "Initial version",
            "productionDate": "Production Date",
            "lastUpdateTime": "2009-05-18T20:36:33Z",
            "releaseTime": "2009-05-18T00:00:00Z",
            "createTime": "2007-08-28T15:19:57Z",
            "license": "NONE",
            "citationRequirements": "Research publications, news or magazine articles and radio or television broadcasts employing statistical summaries of the Odum Institute data should give an appropriate citation to the Institute as the source of the data.",
            "conditions": "Files are publicly available.  Institute staff <B>are not</B> available to assist extramural clients with accessing and using these files.",
            "disclaimer": "Files are offered \"as is\" with no warranty or claim of fitness for any purpose. In no event shall the University be liable for any actual, incidental or consequential damages arising from use of these files.",
            "fileAccessRequest": false,
            "metadataBlocks": {
                "citation": {
                    "displayName": "Citation Metadata",
                    "fields": [
                        {
                            "typeName": "title",
                            "multiple": false,
                            "typeClass": "primitive",
                            "value": "Election and Media Impact Studies (CAPS-ELECT1 CAPS-ELECT2 CAPS-ELECT3 CAPS-ELECT4 CAPS-ELECT5 and CAPS-SETH1 CAPS-SETH2 CAPS-SETH3 CAPS-SETH4 CAPS-SETH5 module)"
                        },
                        {
                            "typeName": "otherId",
                            "multiple": true,
                            "typeClass": "compound",
                            "value": [
                                {
                                    "otherIdAgency": {
                                        "typeName": "otherIdAgency",
                                        "multiple": false,
                                        "typeClass": "primitive",
                                        "value": "odum"
                                    },
                                    "otherIdValue": {
                                        "typeName": "otherIdValue",
                                        "multiple": false,
                                        "typeClass": "primitive",
                                        "value": "CAPS-ELECT"
                                    }
                                },
                                {
                                    "otherIdAgency": {
                                        "typeName": "otherIdAgency",
                                        "multiple": false,
                                        "typeClass": "primitive",
                                        "value": "odum:extended"
                                    },
                                    "otherIdValue": {
                                        "typeName": "otherIdValue",
                                        "multiple": false,
                                        "typeClass": "primitive",
                                        "value": "CAPS-ELECT1 CAPS-ELECT2 CAPS-ELECT3 CAPS-ELECT4 CAPS-ELECT5 CAPS-SETH1 CAPS-SETH2 CAPS-SETH3 CAPS-SETH4 CAPS-SETH5"
                                    }
                                }
                            ]
                        },
                        {
                            "typeName": "author",
                            "multiple": true,
                            "typeClass": "compound",
                            "value": [
                                {
                                    "authorName": {
                                        "typeName": "authorName",
                                        "multiple": false,
                                        "typeClass": "primitive",
                                        "value": "N/A"
                                    }
                                }
                            ]
                        },
                        {
                            "typeName": "datasetContact",
                            "multiple": true,
                            "typeClass": "compound",
                            "value": [
                                {
                                    "datasetContactEmail": {
                                        "typeName": "datasetContactEmail",
                                        "multiple": false,
                                        "typeClass": "primitive",
                                        "value": "N/A"
                                    }
                                }
                            ]
                        },
                        {
                            "typeName": "dsDescription",
                            "multiple": true,
                            "typeClass": "compound",
                            "value": [
                                {
                                    "dsDescriptionValue": {
                                        "typeName": "dsDescriptionValue",
                                        "multiple": false,
                                        "typeClass": "primitive",
                                        "value": "<p>ELECT1 is the first unit of a five-unit project designed to investigate the impact of the mass media and interpersonal communication on a representative sample of UNC undergraduates during the final weeks of the 1986 general elections. In the five units, students are questioned weekly about changes in their commitment to candidates running for the U.S. Senate, House of Representatives, and State Supreme Court. The study will replicate a CAPS/84 study that focused on the Reagan-Mondale, Helms-\nHunt, and Martin-Edmisten campaigns.</p><p>ELECT1 contains questions about how interested the R is in the elections, who they favored in last spring's Senate primary, whether they voted in the primary elections last spring, if/where they expect to vote in November. In addition, the R is asked how committed they are to voting for Broyhill or Sanford in the Senate race, whether that response would have been the same 2 weeks ago. If the latter answer is no, respondents are asked to recall their pas\nt degree of commitment, what new information led them to change their minds, and whether everyone in their family agrees with their voting preference for the Senate race. A similar series of questions are asked about whether the R favors the Democratic or Republican candidate in the House election. A first question asks what district the R plans to vote in.\n</p><p>In subsequent ELECT units Rs are asked about their commitment to candidates. If commitment has changed they are asked to explain why and their sources of information.</p><p>The 1985 SETH units are very similar to the ELECT units.</p><p>No standard scoring.</p><p>See codebook for more information.</p>"
                                    }
                                }
                            ]
                        },
                        {
                            "typeName": "keyword",
                            "multiple": true,
                            "typeClass": "compound",
                            "value": [
                                {
                                    "keywordValue": {
                                        "typeName": "keywordValue",
                                        "multiple": false,
                                        "typeClass": "primitive",
                                        "value": "Elections"
                                    },
                                    "keywordVocabulary": {
                                        "typeName": "keywordVocabulary",
                                        "multiple": false,
                                        "typeClass": "primitive",
                                        "value": "ODUM:INDEX.TERMS"
                                    }
                                },
                                {
                                    "keywordValue": {
                                        "typeName": "keywordValue",
                                        "multiple": false,
                                        "typeClass": "primitive",
                                        "value": "Politics"
                                    },
                                    "keywordVocabulary": {
                                        "typeName": "keywordVocabulary",
                                        "multiple": false,
                                        "typeClass": "primitive",
                                        "value": "ODUM:INDEX.TERMS"
                                    }
                                },
                                {
                                    "keywordValue": {
                                        "typeName": "keywordValue",
                                        "multiple": false,
                                        "typeClass": "primitive",
                                        "value": "Voting"
                                    },
                                    "keywordVocabulary": {
                                        "typeName": "keywordVocabulary",
                                        "multiple": false,
                                        "typeClass": "primitive",
                                        "value": "ODUM:INDEX.TERMS"
                                    }
                                },
                                {
                                    "keywordValue": {
                                        "typeName": "keywordValue",
                                        "multiple": false,
                                        "typeClass": "primitive",
                                        "value": "Political communication"
                                    },
                                    "keywordVocabulary": {
                                        "typeName": "keywordVocabulary",
                                        "multiple": false,
                                        "typeClass": "primitive",
                                        "value": "ODUM:INDEX.TERMS"
                                    }
                                },
                                {
                                    "keywordValue": {
                                        "typeName": "keywordValue",
                                        "multiple": false,
                                        "typeClass": "primitive",
                                        "value": "Political campaign"
                                    },
                                    "keywordVocabulary": {
                                        "typeName": "keywordVocabulary",
                                        "multiple": false,
                                        "typeClass": "primitive",
                                        "value": "ODUM:INDEX.TERMS"
                                    }
                                },
                                {
                                    "keywordValue": {
                                        "typeName": "keywordValue",
                                        "multiple": false,
                                        "typeClass": "primitive",
                                        "value": "Mass media"
                                    },
                                    "keywordVocabulary": {
                                        "typeName": "keywordVocabulary",
                                        "multiple": false,
                                        "typeClass": "primitive",
                                        "value": "ODUM:INDEX.TERMS"
                                    }
                                },
                                {
                                    "keywordValue": {
                                        "typeName": "keywordValue",
                                        "multiple": false,
                                        "typeClass": "primitive",
                                        "value": "Diffusion of information"
                                    },
                                    "keywordVocabulary": {
                                        "typeName": "keywordVocabulary",
                                        "multiple": false,
                                        "typeClass": "primitive",
                                        "value": "ODUM:INDEX.TERMS"
                                    }
                                },
                                {
                                    "keywordValue": {
                                        "typeName": "keywordValue",
                                        "multiple": false,
                                        "typeClass": "primitive",
                                        "value": "Information processing"
                                    },
                                    "keywordVocabulary": {
                                        "typeName": "keywordVocabulary",
                                        "multiple": false,
                                        "typeClass": "primitive",
                                        "value": "ODUM:INDEX.TERMS"
                                    }
                                },
                                {
                                    "keywordValue": {
                                        "typeName": "keywordValue",
                                        "multiple": false,
                                        "typeClass": "primitive",
                                        "value": "Opinion leaders"
                                    },
                                    "keywordVocabulary": {
                                        "typeName": "keywordVocabulary",
                                        "multiple": false,
                                        "typeClass": "primitive",
                                        "value": "ODUM:INDEX.TERMS"
                                    }
                                },
                                {
                                    "keywordValue": {
                                        "typeName": "keywordValue",
                                        "multiple": false,
                                        "typeClass": "primitive",
                                        "value": "Personal influence"
                                    },
                                    "keywordVocabulary": {
                                        "typeName": "keywordVocabulary",
                                        "multiple": false,
                                        "typeClass": "primitive",
                                        "value": "ODUM:INDEX.TERMS"
                                    }
                                },
                                {
                                    "keywordValue": {
                                        "typeName": "keywordValue",
                                        "multiple": false,
                                        "typeClass": "primitive",
                                        "value": "Voting panel studies"
                                    },
                                    "keywordVocabulary": {
                                        "typeName": "keywordVocabulary",
                                        "multiple": false,
                                        "typeClass": "primitive",
                                        "value": "ODUM:INDEX.TERMS"
                                    }
                                }
                            ]
                        },
                        {
                            "typeName": "publication",
                            "multiple": true,
                            "typeClass": "compound",
                            "value": [
                                {
                                    "publicationCitation": {
                                        "typeName": "publicationCitation",
                                        "multiple": false,
                                        "typeClass": "primitive",
                                        "value": "Finn, S. (1986) Electoral Information Flow and Students Information Processing: A Computerized Panel Study. In M. L. McLaughlin (Ed.), Communication Yearbook 10. Beverly Hills: Sage."
                                    }
                                }
                            ]
                        },
                        {
                            "typeName": "productionDate",
                            "multiple": false,
                            "typeClass": "primitive",
                            "value": "1988"
                        },
                        {
                            "typeName": "productionPlace",
                            "multiple": false,
                            "typeClass": "primitive",
                            "value": "Chapel Hill, NC"
                        },
                        {
                            "typeName": "distributor",
                            "multiple": true,
                            "typeClass": "compound",
                            "value": [
                                {
                                    "distributorName": {
                                        "typeName": "distributorName",
                                        "multiple": false,
                                        "typeClass": "primitive",
                                        "value": "Odum Institute"
                                    }
                                }
                            ]
                        }
                    ]
                }
            },
            "files": [
                {
                    "description": "",
                    "label": "caps_1985_seth1_data",
                    "restricted": false,
                    "version": 1,
                    "datasetVersionId": 3432,
                    "categories": [
                        "Data File (1985)"
                    ],
                    "dataFile": {
                        "id": 8398,
                        "persistentId": "",
                        "pidURL": "",
                        "filename": "caps_1985_seth1_data",
                        "contentType": "text/plain",
                        "filesize": 94900,
                        "description": "",
                        "storageIdentifier": "caps_1985_seth1_data",
                        "rootDataFileId": -1,
                        "md5": "",
                        "checksum": {
                            "type": "MD5",
                            "value": ""
                        },
                        "creationDate": "2013-02-25"
                    }
                },
                {
                    "description": "",
                    "label": "caps_1985_seth1_sas.export",
                    "restricted": false,
                    "version": 1,
                    "datasetVersionId": 3432,
                    "categories": [
                        "SAS Export Library (1985)"
                    ],
                    "dataFile": {
                        "id": 8403,
                        "persistentId": "",
                        "pidURL": "",
                        "filename": "caps_1985_seth1_sas.export",
                        "contentType": "application/x-sas-transport",
                        "filesize": 225040,
                        "description": "",
                        "storageIdentifier": "caps_1985_seth1_sas.export",
                        "rootDataFileId": -1,
                        "md5": "",
                        "checksum": {
                            "type": "MD5",
                            "value": ""
                        },
                        "creationDate": "2013-02-25"
                    }
                },
                {
                    "description": "",
                    "label": "caps_1985_seth1_source",
                    "restricted": false,
                    "version": 1,
                    "datasetVersionId": 3432,
                    "categories": [
                        "Question Text and/or Programming Statements (1985)"
                    ],
                    "dataFile": {
                        "id": 8382,
                        "persistentId": "",
                        "pidURL": "",
                        "filename": "caps_1985_seth1_source",
                        "contentType": "text/plain",
                        "filesize": 34314,
                        "description": "",
                        "storageIdentifier": "caps_1985_seth1_source",
                        "rootDataFileId": -1,
                        "md5": "",
                        "checksum": {
                            "type": "MD5",
                            "value": ""
                        },
                        "creationDate": "2013-02-25"
                    }
                },
                {
                    "description": "",
                    "label": "caps_1985_seth1_spss.portable",
                    "restricted": false,
                    "version": 1,
                    "datasetVersionId": 3432,
                    "categories": [
                        "SPSS Portable File (1985)"
                    ],
                    "dataFile": {
                        "id": 8405,
                        "persistentId": "",
                        "pidURL": "",
                        "filename": "caps_1985_seth1_spss.portable",
                        "contentType": "application/x-spss-por",
                        "filesize": 27470,
                        "description": "",
                        "storageIdentifier": "caps_1985_seth1_spss.portable",
                        "rootDataFileId": -1,
                        "md5": "",
                        "checksum": {
                            "type": "MD5",
                            "value": ""
                        },
                        "creationDate": "2013-02-25"
                    }
                },
                {
                    "label": "caps_1985_seth1_spss.tab",
                    "restricted": false,
                    "version": 1,
                    "datasetVersionId": 3432,
                    "categories": [
                        "Data File 1 (caps_1985_seth1_spss.portable)"
                    ],
                    "dataFile": {
                        "id": 8388,
                        "persistentId": "",
                        "pidURL": "",
                        "filename": "caps_1985_seth1_spss.tab",
                        "contentType": "text/tab-separated-values",
                        "filesize": 24465,
                        "storageIdentifier": "caps_1985_seth1_spss.tab",
                        "originalFileFormat": "application/x-spss-por",
                        "originalFormatLabel": "SPSS Portable",
                        "UNF": "UNF:3:jKOxYkDNSA4JejkUdUP4hg==",
                        "rootDataFileId": -1,
                        "md5": "",
                        "checksum": {
                            "type": "MD5",
                            "value": ""
                        },
                        "creationDate": "2013-02-25"
                    }
                },
                {
                    "description": "",
                    "label": "caps_1985_seth2_sas.export",
                    "restricted": false,
                    "version": 1,
                    "datasetVersionId": 3432,
                    "categories": [
                        "SAS Export Library (1985)"
                    ],
                    "dataFile": {
                        "id": 8367,
                        "persistentId": "",
                        "pidURL": "",
                        "filename": "caps_1985_seth2_sas.export",
                        "contentType": "application/x-sas-transport",
                        "filesize": 37760,
                        "description": "",
                        "storageIdentifier": "caps_1985_seth2_sas.export",
                        "rootDataFileId": -1,
                        "md5": "",
                        "checksum": {
                            "type": "MD5",
                            "value": ""
                        },
                        "creationDate": "2013-02-25"
                    }
                },
                {
                    "description": "",
                    "label": "caps_1985_seth2_source",
                    "restricted": false,
                    "version": 1,
                    "datasetVersionId": 3432,
                    "categories": [
                        "Question Text and/or Programming Statements (1985)"
                    ],
                    "dataFile": {
                        "id": 8409,
                        "persistentId": "",
                        "pidURL": "",
                        "filename": "caps_1985_seth2_source",
                        "contentType": "text/plain",
                        "filesize": 50052,
                        "description": "",
                        "storageIdentifier": "caps_1985_seth2_source",
                        "rootDataFileId": -1,
                        "md5": "",
                        "checksum": {
                            "type": "MD5",
                            "value": ""
                        },
                        "creationDate": "2013-02-25"
                    }
                },
                {
                    "description": "",
                    "label": "caps_1985_seth2_spss.portable",
                    "restricted": false,
                    "version": 1,
                    "datasetVersionId": 3432,
                    "categories": [
                        "SPSS Portable File (1985)"
                    ],
                    "dataFile": {
                        "id": 8395,
                        "persistentId": "",
                        "pidURL": "",
                        "filename": "caps_1985_seth2_spss.portable",
                        "contentType": "application/x-spss-por",
                        "filesize": 21402,
                        "description": "",
                        "storageIdentifier": "caps_1985_seth2_spss.portable",
                        "rootDataFileId": -1,
                        "md5": "",
                        "checksum": {
                            "type": "MD5",
                            "value": ""
                        },
                        "creationDate": "2013-02-25"
                    }
                },
                {
                    "label": "caps_1985_seth2_spss.tab",
                    "restricted": false,
                    "version": 1,
                    "datasetVersionId": 3432,
                    "categories": [
                        "Data File 2 (caps_1985_seth2_spss.portable)"
                    ],
                    "dataFile": {
                        "id": 8397,
                        "persistentId": "",
                        "pidURL": "",
                        "filename": "caps_1985_seth2_spss.tab",
                        "contentType": "text/tab-separated-values",
                        "filesize": 17778,
                        "storageIdentifier": "caps_1985_seth2_spss.tab",
                        "originalFileFormat": "application/x-spss-por",
                        "originalFormatLabel": "SPSS Portable",
                        "UNF": "UNF:3:YiDqPOky7cZQXxuUy3cVSw==",
                        "rootDataFileId": -1,
                        "md5": "",
                        "checksum": {
                            "type": "MD5",
                            "value": ""
                        },
                        "creationDate": "2013-02-25"
                    }
                },
                {
                    "description": "",
                    "label": "caps_1985_seth3_sas.export",
                    "restricted": false,
                    "version": 1,
                    "datasetVersionId": 3432,
                    "categories": [
                        "SAS Export Library (1985)"
                    ],
                    "dataFile": {
                        "id": 8396,
                        "persistentId": "",
                        "pidURL": "",
                        "filename": "caps_1985_seth3_sas.export",
                        "contentType": "application/x-sas-transport",
                        "filesize": 38400,
                        "description": "",
                        "storageIdentifier": "caps_1985_seth3_sas.export",
                        "rootDataFileId": -1,
                        "md5": "",
                        "checksum": {
                            "type": "MD5",
                            "value": ""
                        },
                        "creationDate": "2013-02-25"
                    }
                },
                {
                    "description": "",
                    "label": "caps_1985_seth3_source",
                    "restricted": false,
                    "version": 1,
                    "datasetVersionId": 3432,
                    "categories": [
                        "Question Text and/or Programming Statements (1985)"
                    ],
                    "dataFile": {
                        "id": 8360,
                        "persistentId": "",
                        "pidURL": "",
                        "filename": "caps_1985_seth3_source",
                        "contentType": "text/plain",
                        "filesize": 48117,
                        "description": "",
                        "storageIdentifier": "caps_1985_seth3_source",
                        "rootDataFileId": -1,
                        "md5": "",
                        "checksum": {
                            "type": "MD5",
                            "value": ""
                        },
                        "creationDate": "2013-02-25"
                    }
                },
                {
                    "description": "",
                    "label": "caps_1985_seth3_spss.portable",
                    "restricted": false,
                    "version": 1,
                    "datasetVersionId": 3432,
                    "categories": [
                        "SPSS Portable File (1985)"
                    ],
                    "dataFile": {
                        "id": 8384,
                        "persistentId": "",
                        "pidURL": "",
                        "filename": "caps_1985_seth3_spss.portable",
                        "contentType": "application/x-spss-por",
                        "filesize": 21648,
                        "description": "",
                        "storageIdentifier": "caps_1985_seth3_spss.portable",
                        "rootDataFileId": -1,
                        "md5": "",
                        "checksum": {
                            "type": "MD5",
                            "value": ""
                        },
                        "creationDate": "2013-02-25"
                    }
                },
                {
                    "label": "caps_1985_seth3_spss.tab",
                    "restricted": false,
                    "version": 1,
                    "datasetVersionId": 3432,
                    "categories": [
                        "Data File 3 (caps_1985_seth3_spss.portable)"
                    ],
                    "dataFile": {
                        "id": 8401,
                        "persistentId": "",
                        "pidURL": "",
                        "filename": "caps_1985_seth3_spss.tab",
                        "contentType": "text/tab-separated-values",
                        "filesize": 18038,
                        "storageIdentifier": "caps_1985_seth3_spss.tab",
                        "originalFileFormat": "application/x-spss-por",
                        "originalFormatLabel": "SPSS Portable",
                        "UNF": "UNF:3:2hpfvCQ6SWVKXAQKPpj0tg==",
                        "rootDataFileId": -1,
                        "md5": "",
                        "checksum": {
                            "type": "MD5",
                            "value": ""
                        },
                        "creationDate": "2013-02-25"
                    }
                },
                {
                    "description": "",
                    "label": "caps_1985_seth4_sas.export",
                    "restricted": false,
                    "version": 1,
                    "datasetVersionId": 3432,
                    "categories": [
                        "SAS Export Library (1985)"
                    ],
                    "dataFile": {
                        "id": 8406,
                        "persistentId": "",
                        "pidURL": "",
                        "filename": "caps_1985_seth4_sas.export",
                        "contentType": "application/x-sas-transport",
                        "filesize": 45040,
                        "description": "",
                        "storageIdentifier": "caps_1985_seth4_sas.export",
                        "rootDataFileId": -1,
                        "md5": "",
                        "checksum": {
                            "type": "MD5",
                            "value": ""
                        },
                        "creationDate": "2013-02-25"
                    }
                },
                {
                    "description": "",
                    "label": "caps_1985_seth4_source",
                    "restricted": false,
                    "version": 1,
                    "datasetVersionId": 3432,
                    "categories": [
                        "Question Text and/or Programming Statements (1985)"
                    ],
                    "dataFile": {
                        "id": 8389,
                        "persistentId": "",
                        "pidURL": "",
                        "filename": "caps_1985_seth4_source",
                        "contentType": "text/plain",
                        "filesize": 75465,
                        "description": "",
                        "storageIdentifier": "caps_1985_seth4_source",
                        "rootDataFileId": -1,
                        "md5": "",
                        "checksum": {
                            "type": "MD5",
                            "value": ""
                        },
                        "creationDate": "2013-02-25"
                    }
                },
                {
                    "description": "",
                    "label": "caps_1985_seth4_spss.portable",
                    "restricted": false,
                    "version": 1,
                    "datasetVersionId": 3432,
                    "categories": [
                        "SPSS Portable File (1985)"
                    ],
                    "dataFile": {
                        "id": 8361,
                        "persistentId": "",
                        "pidURL": "",
                        "filename": "caps_1985_seth4_spss.portable",
                        "contentType": "application/x-spss-por",
                        "filesize": 24436,
                        "description": "",
                        "storageIdentifier": "caps_1985_seth4_spss.portable",
                        "rootDataFileId": -1,
                        "md5": "",
                        "checksum": {
                            "type": "MD5",
                            "value": ""
                        },
                        "creationDate": "2013-02-25"
                    }
                },
                {
                    "label": "caps_1985_seth4_spss.tab",
                    "restricted": false,
                    "version": 1,
                    "datasetVersionId": 3432,
                    "categories": [
                        "Data File 4 (caps_1985_seth4_spss.portable)"
                    ],
                    "dataFile": {
                        "id": 8408,
                        "persistentId": "",
                        "pidURL": "",
                        "filename": "caps_1985_seth4_spss.tab",
                        "contentType": "text/tab-separated-values",
                        "filesize": 20291,
                        "storageIdentifier": "caps_1985_seth4_spss.tab",
                        "originalFileFormat": "application/x-spss-por",
                        "originalFormatLabel": "SPSS Portable",
                        "UNF": "UNF:3:EjFVAcYYb+d7GwpaGaAG8A==",
                        "rootDataFileId": -1,
                        "md5": "",
                        "checksum": {
                            "type": "MD5",
                            "value": ""
                        },
                        "creationDate": "2013-02-25"
                    }
                },
                {
                    "description": "",
                    "label": "caps_1985_seth5_data",
                    "restricted": false,
                    "version": 1,
                    "datasetVersionId": 3432,
                    "categories": [
                        "Data File (1985)"
                    ],
                    "dataFile": {
                        "id": 8393,
                        "persistentId": "",
                        "pidURL": "",
                        "filename": "caps_1985_seth5_data",
                        "contentType": "text/plain",
                        "filesize": 145600,
                        "description": "",
                        "storageIdentifier": "caps_1985_seth5_data",
                        "rootDataFileId": -1,
                        "md5": "",
                        "checksum": {
                            "type": "MD5",
                            "value": ""
                        },
                        "creationDate": "2013-02-25"
                    }
                },
                {
                    "description": "",
                    "label": "caps_1985_seth5_sas.export",
                    "restricted": false,
                    "version": 1,
                    "datasetVersionId": 3432,
                    "categories": [
                        "SAS Export Library (1985)"
                    ],
                    "dataFile": {
                        "id": 8373,
                        "persistentId": "",
                        "pidURL": "",
                        "filename": "caps_1985_seth5_sas.export",
                        "contentType": "application/x-sas-transport",
                        "filesize": 232480,
                        "description": "",
                        "storageIdentifier": "caps_1985_seth5_sas.export",
                        "rootDataFileId": -1,
                        "md5": "",
                        "checksum": {
                            "type": "MD5",
                            "value": ""
                        },
                        "creationDate": "2013-02-25"
                    }
                },
                {
                    "description": "",
                    "label": "caps_1985_seth5_source",
                    "restricted": false,
                    "version": 1,
                    "datasetVersionId": 3432,
                    "categories": [
                        "Question Text and/or Programming Statements (1985)"
                    ],
                    "dataFile": {
                        "id": 8371,
                        "persistentId": "",
                        "pidURL": "",
                        "filename": "caps_1985_seth5_source",
                        "contentType": "text/plain",
                        "filesize": 37023,
                        "description": "",
                        "storageIdentifier": "caps_1985_seth5_source",
                        "rootDataFileId": -1,
                        "md5": "",
                        "checksum": {
                            "type": "MD5",
                            "value": ""
                        },
                        "creationDate": "2013-02-25"
                    }
                },
                {
                    "description": "",
                    "label": "caps_1985_seth5_spss.portable",
                    "restricted": false,
                    "version": 1,
                    "datasetVersionId": 3432,
                    "categories": [
                        "SPSS Portable File (1985)"
                    ],
                    "dataFile": {
                        "id": 8385,
                        "persistentId": "",
                        "pidURL": "",
                        "filename": "caps_1985_seth5_spss.portable",
                        "contentType": "application/x-spss-por",
                        "filesize": 43050,
                        "description": "",
                        "storageIdentifier": "caps_1985_seth5_spss.portable",
                        "rootDataFileId": -1,
                        "md5": "",
                        "checksum": {
                            "type": "MD5",
                            "value": ""
                        },
                        "creationDate": "2013-02-25"
                    }
                },
                {
                    "label": "caps_1985_seth5_spss.tab",
                    "restricted": false,
                    "version": 1,
                    "datasetVersionId": 3432,
                    "categories": [
                        "Data File 5 (caps_1985_seth5_spss.portable)"
                    ],
                    "dataFile": {
                        "id": 8391,
                        "persistentId": "",
                        "pidURL": "",
                        "filename": "caps_1985_seth5_spss.tab",
                        "contentType": "text/tab-separated-values",
                        "filesize": 38988,
                        "storageIdentifier": "caps_1985_seth5_spss.tab",
                        "originalFileFormat": "application/x-spss-por",
                        "originalFormatLabel": "SPSS Portable",
                        "UNF": "UNF:3:zWDM6Jfd1cpDuNZkAbGHJA==",
                        "rootDataFileId": -1,
                        "md5": "",
                        "checksum": {
                            "type": "MD5",
                            "value": ""
                        },
                        "creationDate": "2013-02-25"
                    }
                },
                {
                    "description": "",
                    "label": "caps_1985_sethnc2_data",
                    "restricted": false,
                    "version": 1,
                    "datasetVersionId": 3432,
                    "categories": [
                        "Data File (1985)"
                    ],
                    "dataFile": {
                        "id": 8377,
                        "persistentId": "",
                        "pidURL": "",
                        "filename": "caps_1985_sethnc2_data",
                        "contentType": "text/plain",
                        "filesize": 42900,
                        "description": "",
                        "storageIdentifier": "caps_1985_sethnc2_data",
                        "rootDataFileId": -1,
                        "md5": "",
                        "checksum": {
                            "type": "MD5",
                            "value": ""
                        },
                        "creationDate": "2013-02-25"
                    }
                },
                {
                    "description": "",
                    "label": "caps_1985_sethnc3_data",
                    "restricted": false,
                    "version": 1,
                    "datasetVersionId": 3432,
                    "categories": [
                        "Data File (1985)"
                    ],
                    "dataFile": {
                        "id": 8404,
                        "persistentId": "",
                        "pidURL": "",
                        "filename": "caps_1985_sethnc3_data",
                        "contentType": "text/plain",
                        "filesize": 40300,
                        "description": "",
                        "storageIdentifier": "caps_1985_sethnc3_data",
                        "rootDataFileId": -1,
                        "md5": "",
                        "checksum": {
                            "type": "MD5",
                            "value": ""
                        },
                        "creationDate": "2013-02-25"
                    }
                },
                {
                    "description": "",
                    "label": "caps_1985_sethnc4_data",
                    "restricted": false,
                    "version": 1,
                    "datasetVersionId": 3432,
                    "categories": [
                        "Data File (1985)"
                    ],
                    "dataFile": {
                        "id": 8379,
                        "persistentId": "",
                        "pidURL": "",
                        "filename": "caps_1985_sethnc4_data",
                        "contentType": "text/plain",
                        "filesize": 43680,
                        "description": "",
                        "storageIdentifier": "caps_1985_sethnc4_data",
                        "rootDataFileId": -1,
                        "md5": "",
                        "checksum": {
                            "type": "MD5",
                            "value": ""
                        },
                        "creationDate": "2013-02-25"
                    }
                },
                {
                    "description": "",
                    "label": "caps_1985_sethout2_data",
                    "restricted": false,
                    "version": 1,
                    "datasetVersionId": 3432,
                    "categories": [
                        "Data File (1985)"
                    ],
                    "dataFile": {
                        "id": 8363,
                        "persistentId": "",
                        "pidURL": "",
                        "filename": "caps_1985_sethout2_data",
                        "contentType": "text/plain",
                        "filesize": 5070,
                        "description": "",
                        "storageIdentifier": "caps_1985_sethout2_data",
                        "rootDataFileId": -1,
                        "md5": "",
                        "checksum": {
                            "type": "MD5",
                            "value": ""
                        },
                        "creationDate": "2013-02-25"
                    }
                },
                {
                    "description": "",
                    "label": "caps_1985_sethout3_data",
                    "restricted": false,
                    "version": 1,
                    "datasetVersionId": 3432,
                    "categories": [
                        "Data File (1985)"
                    ],
                    "dataFile": {
                        "id": 8390,
                        "persistentId": "",
                        "pidURL": "",
                        "filename": "caps_1985_sethout3_data",
                        "contentType": "text/plain",
                        "filesize": 6110,
                        "description": "",
                        "storageIdentifier": "caps_1985_sethout3_data",
                        "rootDataFileId": -1,
                        "md5": "",
                        "checksum": {
                            "type": "MD5",
                            "value": ""
                        },
                        "creationDate": "2013-02-25"
                    }
                },
                {
                    "description": "",
                    "label": "caps_1985_sethout4_data",
                    "restricted": false,
                    "version": 1,
                    "datasetVersionId": 3432,
                    "categories": [
                        "Data File (1985)"
                    ],
                    "dataFile": {
                        "id": 8386,
                        "persistentId": "",
                        "pidURL": "",
                        "filename": "caps_1985_sethout4_data",
                        "contentType": "text/plain",
                        "filesize": 6630,
                        "description": "",
                        "storageIdentifier": "caps_1985_sethout4_data",
                        "rootDataFileId": -1,
                        "md5": "",
                        "checksum": {
                            "type": "MD5",
                            "value": ""
                        },
                        "creationDate": "2013-02-25"
                    }
                },
                {
                    "description": "",
                    "label": "caps_1987_elect1_data",
                    "restricted": false,
                    "version": 1,
                    "datasetVersionId": 3432,
                    "categories": [
                        "Data File (1987)"
                    ],
                    "dataFile": {
                        "id": 8374,
                        "persistentId": "",
                        "pidURL": "",
                        "filename": "caps_1987_elect1_data",
                        "contentType": "text/plain",
                        "filesize": 262080,
                        "description": "",
                        "storageIdentifier": "caps_1987_elect1_data",
                        "rootDataFileId": -1,
                        "md5": "",
                        "checksum": {
                            "type": "MD5",
                            "value": ""
                        },
                        "creationDate": "2013-02-25"
                    }
                },
                {
                    "description": "",
                    "label": "caps_1987_elect1_freqjcl",
                    "restricted": false,
                    "version": 1,
                    "datasetVersionId": 3432,
                    "categories": [
                        "SAS Control Cards (1987)"
                    ],
                    "dataFile": {
                        "id": 8368,
                        "persistentId": "",
                        "pidURL": "",
                        "filename": "caps_1987_elect1_freqjcl",
                        "contentType": "text/x-sas-syntax",
                        "filesize": 8490,
                        "description": "",
                        "storageIdentifier": "caps_1987_elect1_freqjcl",
                        "rootDataFileId": -1,
                        "md5": "",
                        "checksum": {
                            "type": "MD5",
                            "value": ""
                        },
                        "creationDate": "2013-02-25"
                    }
                },
                {
                    "description": "",
                    "label": "caps_1987_elect1_sas.export",
                    "restricted": false,
                    "version": 1,
                    "datasetVersionId": 3432,
                    "categories": [
                        "SAS Export Library (1987)"
                    ],
                    "dataFile": {
                        "id": 8411,
                        "persistentId": "",
                        "pidURL": "",
                        "filename": "caps_1987_elect1_sas.export",
                        "contentType": "application/x-sas-transport",
                        "filesize": 96480,
                        "description": "",
                        "storageIdentifier": "caps_1987_elect1_sas.export",
                        "rootDataFileId": -1,
                        "md5": "",
                        "checksum": {
                            "type": "MD5",
                            "value": ""
                        },
                        "creationDate": "2013-02-25"
                    }
                },
                {
                    "description": "",
                    "label": "caps_1987_elect1_source",
                    "restricted": false,
                    "version": 1,
                    "datasetVersionId": 3432,
                    "categories": [
                        "Question Text and/or Programming Statements (1987)"
                    ],
                    "dataFile": {
                        "id": 8394,
                        "persistentId": "",
                        "pidURL": "",
                        "filename": "caps_1987_elect1_source",
                        "contentType": "text/plain",
                        "filesize": 18663,
                        "description": "",
                        "storageIdentifier": "caps_1987_elect1_source",
                        "rootDataFileId": -1,
                        "md5": "",
                        "checksum": {
                            "type": "MD5",
                            "value": ""
                        },
                        "creationDate": "2013-02-25"
                    }
                },
                {
                    "description": "",
                    "label": "caps_1987_elect1_spss.portable",
                    "restricted": false,
                    "version": 1,
                    "datasetVersionId": 3432,
                    "categories": [
                        "SPSS Portable File (1987)"
                    ],
                    "dataFile": {
                        "id": 8399,
                        "persistentId": "",
                        "pidURL": "",
                        "filename": "caps_1987_elect1_spss.portable",
                        "contentType": "application/x-spss-por",
                        "filesize": 20664,
                        "description": "",
                        "storageIdentifier": "caps_1987_elect1_spss.portable",
                        "rootDataFileId": -1,
                        "md5": "",
                        "checksum": {
                            "type": "MD5",
                            "value": ""
                        },
                        "creationDate": "2013-02-25"
                    }
                },
                {
                    "label": "caps_1987_elect1_spss.tab",
                    "restricted": false,
                    "version": 1,
                    "datasetVersionId": 3432,
                    "categories": [
                        "Data File 6 (caps_1987_elect1_spss.portable)"
                    ],
                    "dataFile": {
                        "id": 8414,
                        "persistentId": "",
                        "pidURL": "",
                        "filename": "caps_1987_elect1_spss.tab",
                        "contentType": "text/tab-separated-values",
                        "filesize": 17287,
                        "storageIdentifier": "caps_1987_elect1_spss.tab",
                        "originalFileFormat": "application/x-spss-por",
                        "originalFormatLabel": "SPSS Portable",
                        "UNF": "UNF:3:+yEQ9qw5ELqOkayOOL4Uyw==",
                        "rootDataFileId": -1,
                        "md5": "",
                        "checksum": {
                            "type": "MD5",
                            "value": ""
                        },
                        "creationDate": "2013-02-25"
                    }
                },
                {
                    "description": "",
                    "label": "caps_1987_elect2_data",
                    "restricted": false,
                    "version": 1,
                    "datasetVersionId": 3432,
                    "categories": [
                        "Data File (1987)"
                    ],
                    "dataFile": {
                        "id": 8410,
                        "persistentId": "",
                        "pidURL": "",
                        "filename": "caps_1987_elect2_data",
                        "contentType": "text/plain",
                        "filesize": 331760,
                        "description": "",
                        "storageIdentifier": "caps_1987_elect2_data",
                        "rootDataFileId": -1,
                        "md5": "",
                        "checksum": {
                            "type": "MD5",
                            "value": ""
                        },
                        "creationDate": "2013-02-25"
                    }
                },
                {
                    "description": "",
                    "label": "caps_1987_elect2_freqjcl",
                    "restricted": false,
                    "version": 1,
                    "datasetVersionId": 3432,
                    "categories": [
                        "SAS Control Cards (1987)"
                    ],
                    "dataFile": {
                        "id": 8381,
                        "persistentId": "",
                        "pidURL": "",
                        "filename": "caps_1987_elect2_freqjcl",
                        "contentType": "text/x-sas-syntax",
                        "filesize": 7926,
                        "description": "",
                        "storageIdentifier": "caps_1987_elect2_freqjcl",
                        "rootDataFileId": -1,
                        "md5": "",
                        "checksum": {
                            "type": "MD5",
                            "value": ""
                        },
                        "creationDate": "2013-02-25"
                    }
                },
                {
                    "description": "",
                    "label": "caps_1987_elect2_sas.export",
                    "restricted": false,
                    "version": 1,
                    "datasetVersionId": 3432,
                    "categories": [
                        "SAS Export Library (1987)"
                    ],
                    "dataFile": {
                        "id": 8370,
                        "persistentId": "",
                        "pidURL": "",
                        "filename": "caps_1987_elect2_sas.export",
                        "contentType": "application/x-sas-transport",
                        "filesize": 176480,
                        "description": "",
                        "storageIdentifier": "caps_1987_elect2_sas.export",
                        "rootDataFileId": -1,
                        "md5": "",
                        "checksum": {
                            "type": "MD5",
                            "value": ""
                        },
                        "creationDate": "2013-02-25"
                    }
                },
                {
                    "description": "",
                    "label": "caps_1987_elect2_source",
                    "restricted": false,
                    "version": 1,
                    "datasetVersionId": 3432,
                    "categories": [
                        "Question Text and/or Programming Statements (1987)"
                    ],
                    "dataFile": {
                        "id": 8387,
                        "persistentId": "",
                        "pidURL": "",
                        "filename": "caps_1987_elect2_source",
                        "contentType": "text/plain",
                        "filesize": 14174,
                        "description": "",
                        "storageIdentifier": "caps_1987_elect2_source",
                        "rootDataFileId": -1,
                        "md5": "",
                        "checksum": {
                            "type": "MD5",
                            "value": ""
                        },
                        "creationDate": "2013-02-25"
                    }
                },
                {
                    "description": "",
                    "label": "caps_1987_elect2_spss.portable",
                    "restricted": false,
                    "version": 1,
                    "datasetVersionId": 3432,
                    "categories": [
                        "SPSS Portable File (1987)"
                    ],
                    "dataFile": {
                        "id": 8375,
                        "persistentId": "",
                        "pidURL": "",
                        "filename": "caps_1987_elect2_spss.portable",
                        "contentType": "application/x-spss-por",
                        "filesize": 25174,
                        "description": "",
                        "storageIdentifier": "caps_1987_elect2_spss.portable",
                        "rootDataFileId": -1,
                        "md5": "",
                        "checksum": {
                            "type": "MD5",
                            "value": ""
                        },
                        "creationDate": "2013-02-25"
                    }
                },
                {
                    "label": "caps_1987_elect2_spss.tab",
                    "restricted": false,
                    "version": 1,
                    "datasetVersionId": 3432,
                    "categories": [
                        "Data File 7 (caps_1987_elect2_spss.portable)"
                    ],
                    "dataFile": {
                        "id": 8378,
                        "persistentId": "",
                        "pidURL": "",
                        "filename": "caps_1987_elect2_spss.tab",
                        "contentType": "text/tab-separated-values",
                        "filesize": 21015,
                        "storageIdentifier": "caps_1987_elect2_spss.tab",
                        "originalFileFormat": "application/x-spss-por",
                        "originalFormatLabel": "SPSS Portable",
                        "UNF": "UNF:3:j36Wb+EY3ybAqAWsdzEDoA==",
                        "rootDataFileId": -1,
                        "md5": "",
                        "checksum": {
                            "type": "MD5",
                            "value": ""
                        },
                        "creationDate": "2013-02-25"
                    }
                },
                {
                    "description": "",
                    "label": "caps_1987_elect3_data",
                    "restricted": false,
                    "version": 1,
                    "datasetVersionId": 3432,
                    "categories": [
                        "Data File (1987)"
                    ],
                    "dataFile": {
                        "id": 8392,
                        "persistentId": "",
                        "pidURL": "",
                        "filename": "caps_1987_elect3_data",
                        "contentType": "text/plain",
                        "filesize": 331760,
                        "description": "",
                        "storageIdentifier": "caps_1987_elect3_data",
                        "rootDataFileId": -1,
                        "md5": "",
                        "checksum": {
                            "type": "MD5",
                            "value": ""
                        },
                        "creationDate": "2013-02-25"
                    }
                },
                {
                    "description": "",
                    "label": "caps_1987_elect3_freqjcl",
                    "restricted": false,
                    "version": 1,
                    "datasetVersionId": 3432,
                    "categories": [
                        "SAS Control Cards (1987)"
                    ],
                    "dataFile": {
                        "id": 8400,
                        "persistentId": "",
                        "pidURL": "",
                        "filename": "caps_1987_elect3_freqjcl",
                        "contentType": "text/x-sas-syntax",
                        "filesize": 7481,
                        "description": "",
                        "storageIdentifier": "caps_1987_elect3_freqjcl",
                        "rootDataFileId": -1,
                        "md5": "",
                        "checksum": {
                            "type": "MD5",
                            "value": ""
                        },
                        "creationDate": "2013-02-25"
                    }
                },
                {
                    "description": "",
                    "label": "caps_1987_elect3_sas.export",
                    "restricted": false,
                    "version": 1,
                    "datasetVersionId": 3432,
                    "categories": [
                        "SAS Export Library (1987)"
                    ],
                    "dataFile": {
                        "id": 8376,
                        "persistentId": "",
                        "pidURL": "",
                        "filename": "caps_1987_elect3_sas.export",
                        "contentType": "application/x-sas-transport",
                        "filesize": 168400,
                        "description": "",
                        "storageIdentifier": "caps_1987_elect3_sas.export",
                        "rootDataFileId": -1,
                        "md5": "",
                        "checksum": {
                            "type": "MD5",
                            "value": ""
                        },
                        "creationDate": "2013-02-25"
                    }
                },
                {
                    "description": "",
                    "label": "caps_1987_elect3_source",
                    "restricted": false,
                    "version": 1,
                    "datasetVersionId": 3432,
                    "categories": [
                        "Question Text and/or Programming Statements (1987)"
                    ],
                    "dataFile": {
                        "id": 8369,
                        "persistentId": "",
                        "pidURL": "",
                        "filename": "caps_1987_elect3_source",
                        "contentType": "text/plain",
                        "filesize": 13765,
                        "description": "",
                        "storageIdentifier": "caps_1987_elect3_source",
                        "rootDataFileId": -1,
                        "md5": "",
                        "checksum": {
                            "type": "MD5",
                            "value": ""
                        },
                        "creationDate": "2013-02-25"
                    }
                },
                {
                    "description": "",
                    "label": "caps_1987_elect3_spss.portable",
                    "restricted": false,
                    "version": 1,
                    "datasetVersionId": 3432,
                    "categories": [
                        "SPSS Portable File (1987)"
                    ],
                    "dataFile": {
                        "id": 8366,
                        "persistentId": "",
                        "pidURL": "",
                        "filename": "caps_1987_elect3_spss.portable",
                        "contentType": "application/x-spss-por",
                        "filesize": 24354,
                        "description": "",
                        "storageIdentifier": "caps_1987_elect3_spss.portable",
                        "rootDataFileId": -1,
                        "md5": "",
                        "checksum": {
                            "type": "MD5",
                            "value": ""
                        },
                        "creationDate": "2013-02-25"
                    }
                },
                {
                    "label": "caps_1987_elect3_spss.tab",
                    "restricted": false,
                    "version": 1,
                    "datasetVersionId": 3432,
                    "categories": [
                        "Data File 8 (caps_1987_elect3_spss.portable)"
                    ],
                    "dataFile": {
                        "id": 8416,
                        "persistentId": "",
                        "pidURL": "",
                        "filename": "caps_1987_elect3_spss.tab",
                        "contentType": "text/tab-separated-values",
                        "filesize": 20283,
                        "storageIdentifier": "caps_1987_elect3_spss.tab",
                        "originalFileFormat": "application/x-spss-por",
                        "originalFormatLabel": "SPSS Portable",
                        "UNF": "UNF:3:HOCDnwXXANIMG6R52NjvDw==",
                        "rootDataFileId": -1,
                        "md5": "",
                        "checksum": {
                            "type": "MD5",
                            "value": ""
                        },
                        "creationDate": "2013-02-25"
                    }
                },
                {
                    "description": "",
                    "label": "caps_1987_elect4_data",
                    "restricted": false,
                    "version": 1,
                    "datasetVersionId": 3432,
                    "categories": [
                        "Data File (1987)"
                    ],
                    "dataFile": {
                        "id": 8362,
                        "persistentId": "",
                        "pidURL": "",
                        "filename": "caps_1987_elect4_data",
                        "contentType": "text/plain",
                        "filesize": 327990,
                        "description": "",
                        "storageIdentifier": "caps_1987_elect4_data",
                        "rootDataFileId": -1,
                        "md5": "",
                        "checksum": {
                            "type": "MD5",
                            "value": ""
                        },
                        "creationDate": "2013-02-25"
                    }
                },
                {
                    "description": "",
                    "label": "caps_1987_elect4_freqjcl",
                    "restricted": false,
                    "version": 1,
                    "datasetVersionId": 3432,
                    "categories": [
                        "SAS Control Cards (1987)"
                    ],
                    "dataFile": {
                        "id": 8412,
                        "persistentId": "",
                        "pidURL": "",
                        "filename": "caps_1987_elect4_freqjcl",
                        "contentType": "text/x-sas-syntax",
                        "filesize": 7394,
                        "description": "",
                        "storageIdentifier": "caps_1987_elect4_freqjcl",
                        "rootDataFileId": -1,
                        "md5": "",
                        "checksum": {
                            "type": "MD5",
                            "value": ""
                        },
                        "creationDate": "2013-02-25"
                    }
                },
                {
                    "description": "",
                    "label": "caps_1987_elect4_sas.export",
                    "restricted": false,
                    "version": 1,
                    "datasetVersionId": 3432,
                    "categories": [
                        "SAS Export Library (1987)"
                    ],
                    "dataFile": {
                        "id": 8365,
                        "persistentId": "",
                        "pidURL": "",
                        "filename": "caps_1987_elect4_sas.export",
                        "contentType": "application/x-sas-transport",
                        "filesize": 145280,
                        "description": "",
                        "storageIdentifier": "caps_1987_elect4_sas.export",
                        "rootDataFileId": -1,
                        "md5": "",
                        "checksum": {
                            "type": "MD5",
                            "value": ""
                        },
                        "creationDate": "2013-02-25"
                    }
                },
                {
                    "description": "",
                    "label": "caps_1987_elect4_source",
                    "restricted": false,
                    "version": 1,
                    "datasetVersionId": 3432,
                    "categories": [
                        "Question Text and/or Programming Statements (1987)"
                    ],
                    "dataFile": {
                        "id": 8372,
                        "persistentId": "",
                        "pidURL": "",
                        "filename": "caps_1987_elect4_source",
                        "contentType": "text/plain",
                        "filesize": 13765,
                        "description": "",
                        "storageIdentifier": "caps_1987_elect4_source",
                        "rootDataFileId": -1,
                        "md5": "",
                        "checksum": {
                            "type": "MD5",
                            "value": ""
                        },
                        "creationDate": "2013-02-25"
                    }
                },
                {
                    "description": "",
                    "label": "caps_1987_elect4_spss.portable",
                    "restricted": false,
                    "version": 1,
                    "datasetVersionId": 3432,
                    "categories": [
                        "SPSS Portable File (1987)"
                    ],
                    "dataFile": {
                        "id": 8359,
                        "persistentId": "",
                        "pidURL": "",
                        "filename": "caps_1987_elect4_spss.portable",
                        "contentType": "application/x-spss-por",
                        "filesize": 23698,
                        "description": "",
                        "storageIdentifier": "caps_1987_elect4_spss.portable",
                        "rootDataFileId": -1,
                        "md5": "",
                        "checksum": {
                            "type": "MD5",
                            "value": ""
                        },
                        "creationDate": "2013-02-25"
                    }
                },
                {
                    "label": "caps_1987_elect4_spss.tab",
                    "restricted": false,
                    "version": 1,
                    "datasetVersionId": 3432,
                    "categories": [
                        "Data File 9 (caps_1987_elect4_spss.portable)"
                    ],
                    "dataFile": {
                        "id": 8413,
                        "persistentId": "",
                        "pidURL": "",
                        "filename": "caps_1987_elect4_spss.tab",
                        "contentType": "text/tab-separated-values",
                        "filesize": 19831,
                        "storageIdentifier": "caps_1987_elect4_spss.tab",
                        "originalFileFormat": "application/x-spss-por",
                        "originalFormatLabel": "SPSS Portable",
                        "UNF": "UNF:3:eBrOYbGpDKRjVID0xcvrjA==",
                        "rootDataFileId": -1,
                        "md5": "",
                        "checksum": {
                            "type": "MD5",
                            "value": ""
                        },
                        "creationDate": "2013-02-25"
                    }
                },
                {
                    "description": "",
                    "label": "caps_1987_elect5_data",
                    "restricted": false,
                    "version": 1,
                    "datasetVersionId": 3432,
                    "categories": [
                        "Data File (1987)"
                    ],
                    "dataFile": {
                        "id": 8364,
                        "persistentId": "",
                        "pidURL": "",
                        "filename": "caps_1987_elect5_data",
                        "contentType": "text/plain",
                        "filesize": 574600,
                        "description": "",
                        "storageIdentifier": "caps_1987_elect5_data",
                        "rootDataFileId": -1,
                        "md5": "",
                        "checksum": {
                            "type": "MD5",
                            "value": ""
                        },
                        "creationDate": "2013-02-25"
                    }
                },
                {
                    "description": "",
                    "label": "caps_1987_elect5_freqjcl",
                    "restricted": false,
                    "version": 1,
                    "datasetVersionId": 3432,
                    "categories": [
                        "SAS Control Cards (1987)"
                    ],
                    "dataFile": {
                        "id": 8380,
                        "persistentId": "",
                        "pidURL": "",
                        "filename": "caps_1987_elect5_freqjcl",
                        "contentType": "text/x-sas-syntax",
                        "filesize": 13346,
                        "description": "",
                        "storageIdentifier": "caps_1987_elect5_freqjcl",
                        "rootDataFileId": -1,
                        "md5": "",
                        "checksum": {
                            "type": "MD5",
                            "value": ""
                        },
                        "creationDate": "2013-02-25"
                    }
                },
                {
                    "description": "",
                    "label": "caps_1987_elect5_sas.export",
                    "restricted": false,
                    "version": 1,
                    "datasetVersionId": 3432,
                    "categories": [
                        "SAS Export Library (1987)"
                    ],
                    "dataFile": {
                        "id": 8383,
                        "persistentId": "",
                        "pidURL": "",
                        "filename": "caps_1987_elect5_sas.export",
                        "contentType": "application/x-sas-transport",
                        "filesize": 201920,
                        "description": "",
                        "storageIdentifier": "caps_1987_elect5_sas.export",
                        "rootDataFileId": -1,
                        "md5": "",
                        "checksum": {
                            "type": "MD5",
                            "value": ""
                        },
                        "creationDate": "2013-02-25"
                    }
                },
                {
                    "description": "",
                    "label": "caps_1987_elect5_source",
                    "restricted": false,
                    "version": 1,
                    "datasetVersionId": 3432,
                    "categories": [
                        "Question Text and/or Programming Statements (1987)"
                    ],
                    "dataFile": {
                        "id": 8407,
                        "persistentId": "",
                        "pidURL": "",
                        "filename": "caps_1987_elect5_source",
                        "contentType": "text/plain",
                        "filesize": 25267,
                        "description": "",
                        "storageIdentifier": "caps_1987_elect5_source",
                        "rootDataFileId": -1,
                        "md5": "",
                        "checksum": {
                            "type": "MD5",
                            "value": ""
                        },
                        "creationDate": "2013-02-25"
                    }
                },
                {
                    "description": "",
                    "label": "caps_1987_elect5_spss.portable",
                    "restricted": false,
                    "version": 1,
                    "datasetVersionId": 3432,
                    "categories": [
                        "SPSS Portable File (1987)"
                    ],
                    "dataFile": {
                        "id": 8415,
                        "persistentId": "",
                        "pidURL": "",
                        "filename": "caps_1987_elect5_spss.portable",
                        "contentType": "application/x-spss-por",
                        "filesize": 35752,
                        "description": "",
                        "storageIdentifier": "caps_1987_elect5_spss.portable",
                        "rootDataFileId": -1,
                        "md5": "",
                        "checksum": {
                            "type": "MD5",
                            "value": ""
                        },
                        "creationDate": "2013-02-25"
                    }
                },
                {
                    "label": "caps_1987_elect5_spss.tab",
                    "restricted": false,
                    "version": 1,
                    "datasetVersionId": 3432,
                    "categories": [
                        "Data File 10 (caps_1987_elect5_spss.portable)"
                    ],
                    "dataFile": {
                        "id": 8402,
                        "persistentId": "",
                        "pidURL": "",
                        "filename": "caps_1987_elect5_spss.tab",
                        "contentType": "text/tab-separated-values",
                        "filesize": 31767,
                        "storageIdentifier": "caps_1987_elect5_spss.tab",
                        "originalFileFormat": "application/x-spss-por",
                        "originalFormatLabel": "SPSS Portable",
                        "UNF": "UNF:3:/Xp4+C1fMZnwoByDs3V6EA==",
                        "rootDataFileId": -1,
                        "md5": "",
                        "checksum": {
                            "type": "MD5",
                            "value": ""
                        },
                        "creationDate": "2013-02-25"
                    }
                }
            ]
        }
    }
}