{
    "status": "OK",
    "data": {
        "persistentUrl": "https://hdl.handle.net/1902.29/D-30484",
        "publisher": "UNC Dataverse",
        "publicationDate": "2007-11-30",
        "datasetVersion": {
            "id": 3614,
            "storageIdentifier": "file://1902.29/D-30484",
            "versionNumber": 1,
            "versionMinorNumber": 0,
            "versionState": "RELEASED",
            "versionNote": "Initial version",
            "distributionDate": "1993",
            "productionDate": "Production Date",
            "lastUpdateTime": "2007-11-30T05:00:00Z",
            "releaseTime": "2007-11-30T00:00:00Z",
            "createTime": "2007-08-28T15:48:23Z",
            "license": "NONE",
            "citationRequirements": "Research publications, news or magazine articles and radio or television broadcasts employing statistical summaries of the Odum Institute data should give an appropriate citation to the Institute as the source of the data.",
            "conditions": "Files are publicly available.  Institute staff <B>are not</B> available to assist extramural clients with accessing and using these files.",
            "disclaimer": "Files are offered \"as is\" with no warranty or claim of fitness for any purpose. In no event shall the University be liable for any actual, incidental or consequential damages arising from use of these files.",
            "fileAccessRequest": false,
            "metadataBlocks": {
                "citation": {
                    "displayName": "Citation Metadata",
                    "fields": [
                        {
                            "typeName": "title",
                            "multiple": false,
                            "typeClass": "primitive",
                            "value": "Carolina Poll, Fall 1993"
                        },
                        {
                            "typeName": "otherId",
                            "multiple": true,
                            "typeClass": "compound",
                            "value": [
                                {
                                    "otherIdAgency": {
                                        "typeName": "otherIdAgency",
                                        "multiple": false,
                                        "typeClass": "primitive",
                                        "value": "odum"
                                    },
                                    "otherIdValue": {
                                        "typeName": "otherIdValue",
                                        "multiple": false,
                                        "typeClass": "primitive",
                                        "value": "D-30484"
                                    }
                                },
                                {
                                    "otherIdAgency": {
                                        "typeName": "otherIdAgency",
                                        "multiple": false,
                                        "typeClass": "primitive",
                                        "value": "odum:extended"
                                    },
                                    "otherIdValue": {
                                        "typeName": "otherIdValue",
                                        "multiple": false,
                                        "typeClass": "primitive",
                                        "value": "NNSP-NC-035"
                                    }
                                }
                            ]
                        },
                        {
                            "typeName": "author",
                            "multiple": true,
                            "typeClass": "compound",
                            "value": [
                                {
                                    "authorName": {
                                        "typeName": "authorName",
                                        "multiple": false,
                                        "typeClass": "primitive",
                                        "value": "School of Journalism and Mass Communication and the Odum Institute for Research in Social Science, University of North Carolina at Chapel Hill"
                                    }
                                }
                            ]
                        },
                        {
                            "typeName": "datasetContact",
                            "multiple": true,
                            "typeClass": "compound",
                            "value": [
                                {
                                    "datasetContactEmail": {
                                        "typeName": "datasetContactEmail",
                                        "multiple": false,
                                        "typeClass": "primitive",
                                        "value": "N/A"
                                    }
                                }
                            ]
                        },
                        {
                            "typeName": "dsDescription",
                            "multiple": true,
                            "typeClass": "compound",
                            "value": [
                                {
                                    "dsDescriptionValue": {
                                        "typeName": "dsDescriptionValue",
                                        "multiple": false,
                                        "typeClass": "primitive",
                                        "value": "<p>This survey asked questions of political and social concerns, including happiness, job satisfaction, computers, child care, sexual harassment, environment, abortion, religion, pets in the home, media use, gun control, unemployment, victim of crime, Anita Hill, Dr, Jack Krevorkian, Ben Chavis, health care reform, and alienation.</p>"
                                    }
                                }
                            ]
                        },
                        {
                            "typeName": "topicClassification",
                            "multiple": true,
                            "typeClass": "compound",
                            "value": [
                                {
                                    "topicClassValue": {
                                        "typeName": "topicClassValue",
                                        "multiple": false,
                                        "typeClass": "primitive",
                                        "value": "Omnibus and public opinion"
                                    },
                                    "topicClassVocab": {
                                        "typeName": "topicClassVocab",
                                        "multiple": false,
                                        "typeClass": "primitive",
                                        "value": "ODUM:MAIN.HEADING"
                                    }
                                },
                                {
                                    "topicClassValue": {
                                        "typeName": "topicClassValue",
                                        "multiple": false,
                                        "typeClass": "primitive",
                                        "value": "Public opinion"
                                    },
                                    "topicClassVocab": {
                                        "typeName": "topicClassVocab",
                                        "multiple": false,
                                        "typeClass": "primitive",
                                        "value": "ODUM:PUBLIC.OPINION.POLLS"
                                    }
                                }
                            ]
                        },
                        {
                            "typeName": "notesText",
                            "multiple": false,
                            "typeClass": "primitive",
                            "value": "Subject: Study Level Error Note, Notes: Telephone survey of adult North Carolinians (age 18+), using next-birthday method of respondent selection within a random sample of households.;Type: ODUM:ACCESS.CATEGORY Notes: I;"
                        },
                        {
                            "typeName": "producer",
                            "multiple": true,
                            "typeClass": "compound",
                            "value": [
                                {
                                    "producerName": {
                                        "typeName": "producerName",
                                        "multiple": false,
                                        "typeClass": "primitive",
                                        "value": "School of Journalism and Mass Communication, University of North Carolina at Chapel Hill"
                                    },
                                    "producerURL": {
                                        "typeName": "producerURL",
                                        "multiple": false,
                                        "typeClass": "primitive",
                                        "value": "http://www.jomc.unc.edu/"
                                    },
                                    "producerLogoURL": {
                                        "typeName": "producerLogoURL",
                                        "multiple": false,
                                        "typeClass": "primitive",
                                        "value": "http://www.jomc.unc.edu/templates/almers_jomc/images/almers_jomc_logo.png"
                                    }
                                }
                            ]
                        },
                        {
                            "typeName": "productionDate",
                            "multiple": false,
                            "typeClass": "primitive",
                            "value": "1993"
                        },
                        {
                            "typeName": "productionPlace",
                            "multiple": false,
                            "typeClass": "primitive",
                            "value": "Chapel Hill, NC"
                        },
                        {
                            "typeName": "distributor",
                            "multiple": true,
                            "typeClass": "compound",
                            "value": [
                                {
                                    "distributorName": {
                                        "typeName": "distributorName",
                                        "multiple": false,
                                        "typeClass": "primitive",
                                        "value": "Odum Institute"
                                    }
                                },
                                {
                                    "distributorName": {
                                        "typeName": "distributorName",
                                        "multiple": false,
                                        "typeClass": "primitive",
                                        "value": "Odum Institute for Research in Social Science"
                                    }
                                }
                            ]
                        },
                        {
                            "typeName": "distributionDate",
                            "multiple": false,
                            "typeClass": "primitive",
                            "value": "1993"
                        },
                        {
                            "typeName": "timePeriodCovered",
                            "multiple": true,
                            "typeClass": "compound",
                            "value": [
                                {
                                    "timePeriodCoveredStart": {
                                        "typeName": "timePeriodCoveredStart",
                                        "multiple": false,
                                        "typeClass": "primitive",
                                        "value": "1993-10"
                                    }
                                }
                            ]
                        },
                        {
                            "typeName": "kindOfData",
                            "multiple": true,
                            "typeClass": "primitive",
                            "value": [
                                "Numeric (Survey)"
                            ]
                        }
                    ]
                },
                "geospatial": {
                    "displayName": "Geospatial Metadata",
                    "fields": [
                        {
                            "typeName": "geographicCoverage",
                            "multiple": true,
                            "typeClass": "compound",
                            "value": [
                                {
                                    "otherGeographicCoverage": {
                                        "typeName": "otherGeographicCoverage",
                                        "multiple": false,
                                        "typeClass": "primitive",
                                        "value": "North Carolina"
                                    }
                                }
                            ]
                        }
                    ]
                }
            },
            "files": [
                {
                    "description": "",
                    "label": "carolina_poll_fall93_data",
                    "restricted": false,
                    "version": 1,
                    "datasetVersionId": 3614,
                    "categories": [
                        "Data, Logical Record"
                    ],
                    "dataFile": {
                        "id": 16662,
                        "persistentId": "",
                        "pidURL": "",
                        "filename": "carolina_poll_fall93_data",
                        "contentType": "text/plain",
                        "filesize": 81675,
                        "description": "",
                        "storageIdentifier": "carolina_poll_fall93_data",
                        "rootDataFileId": -1,
                        "md5": "",
                        "checksum": {
                            "type": "MD5",
                            "value": ""
                        },
                        "creationDate": "2013-02-25"
                    }
                },
                {
                    "description": "",
                    "label": "carolina_poll_fall93_fall93.cdbk",
                    "restricted": false,
                    "version": 1,
                    "datasetVersionId": 3614,
                    "categories": [
                        "Machine-Readable Codebook"
                    ],
                    "dataFile": {
                        "id": 16659,
                        "persistentId": "",
                        "pidURL": "",
                        "filename": "carolina_poll_fall93_fall93.cdbk",
                        "contentType": "text/plain",
                        "filesize": 45012,
                        "description": "",
                        "storageIdentifier": "carolina_poll_fall93_fall93.cdbk",
                        "rootDataFileId": -1,
                        "md5": "",
                        "checksum": {
                            "type": "MD5",
                            "value": ""
                        },
                        "creationDate": "2013-02-25"
                    }
                },
                {
                    "description": "",
                    "label": "carolina_poll_fall93_freqs.pdf",
                    "restricted": false,
                    "version": 1,
                    "datasetVersionId": 3614,
                    "categories": [
                        "Frequencies, PDF File"
                    ],
                    "dataFile": {
                        "id": 16663,
                        "persistentId": "",
                        "pidURL": "",
                        "filename": "carolina_poll_fall93_freqs.pdf",
                        "contentType": "application/pdf",
                        "filesize": 444201,
                        "description": "",
                        "storageIdentifier": "carolina_poll_fall93_freqs.pdf",
                        "rootDataFileId": -1,
                        "md5": "",
                        "checksum": {
                            "type": "MD5",
                            "value": ""
                        },
                        "creationDate": "2013-02-25"
                    }
                },
                {
                    "description": "",
                    "label": "carolina_poll_fall93_quest.pdf",
                    "restricted": false,
                    "version": 1,
                    "datasetVersionId": 3614,
                    "categories": [
                        "Questionnaire, PDF File"
                    ],
                    "dataFile": {
                        "id": 16665,
                        "persistentId": "",
                        "pidURL": "",
                        "filename": "carolina_poll_fall93_quest.pdf",
                        "contentType": "application/pdf",
                        "filesize": 623502,
                        "description": "",
                        "storageIdentifier": "carolina_poll_fall93_quest.pdf",
                        "rootDataFileId": -1,
                        "md5": "",
                        "checksum": {
                            "type": "MD5",
                            "value": ""
                        },
                        "creationDate": "2013-02-25"
                    }
                },
                {
                    "description": "",
                    "label": "carolina_poll_fall93_sas.export",
                    "restricted": false,
                    "version": 1,
                    "datasetVersionId": 3614,
                    "categories": [
                        "SAS Export File"
                    ],
                    "dataFile": {
                        "id": 16664,
                        "persistentId": "",
                        "pidURL": "",
                        "filename": "carolina_poll_fall93_sas.export",
                        "contentType": "application/x-sas-transport",
                        "filesize": 550880,
                        "description": "",
                        "storageIdentifier": "carolina_poll_fall93_sas.export",
                        "rootDataFileId": -1,
                        "md5": "",
                        "checksum": {
                            "type": "MD5",
                            "value": ""
                        },
                        "creationDate": "2013-02-25"
                    }
                },
                {
                    "description": "",
                    "label": "carolina_poll_fall93_spss.portable",
                    "restricted": false,
                    "version": 1,
                    "datasetVersionId": 3614,
                    "categories": [
                        "SPSS Portable File"
                    ],
                    "dataFile": {
                        "id": 16660,
                        "persistentId": "",
                        "pidURL": "",
                        "filename": "carolina_poll_fall93_spss.portable",
                        "contentType": "application/x-spss-por",
                        "filesize": 148311,
                        "description": "",
                        "storageIdentifier": "carolina_poll_fall93_spss.portable",
                        "rootDataFileId": -1,
                        "md5": "",
                        "checksum": {
                            "type": "MD5",
                            "value": ""
                        },
                        "creationDate": "2013-02-25"
                    }
                },
                {
                    "label": "carolina_poll_fall93_spss.tab",
                    "restricted": false,
                    "version": 1,
                    "datasetVersionId": 3614,
                    "categories": [
                        "Data File 1 (carolina_poll_fall93_spss.portable)"
                    ],
                    "dataFile": {
                        "id": 16661,
                        "persistentId": "",
                        "pidURL": "",
                        "filename": "carolina_poll_fall93_spss.tab",
                        "contentType": "text/tab-separated-values",
                        "filesize": 141461,
                        "storageIdentifier": "carolina_poll_fall93_spss.tab",
                        "originalFileFormat": "application/x-spss-por",
                        "originalFormatLabel": "SPSS Portable",
                        "UNF": "UNF:3:55kyRMCmtlyIYzm2a0sOFg==",
                        "rootDataFileId": -1,
                        "md5": "",
                        "checksum": {
                            "type": "MD5",
                            "value": ""
                        },
                        "creationDate": "2013-02-25"
                    }
                },
                {
                    "description": "",
                    "label": "carolina_poll_fall93_studydoc.pdf",
                    "restricted": false,
                    "version": 1,
                    "datasetVersionId": 3614,
                    "categories": [
                        "Study Documentation, PDF File"
                    ],
                    "dataFile": {
                        "id": 16658,
                        "persistentId": "",
                        "pidURL": "",
                        "filename": "carolina_poll_fall93_studydoc.pdf",
                        "contentType": "application/pdf",
                        "filesize": 279366,
                        "description": "",
                        "storageIdentifier": "carolina_poll_fall93_studydoc.pdf",
                        "rootDataFileId": -1,
                        "md5": "",
                        "checksum": {
                            "type": "MD5",
                            "value": ""
                        },
                        "creationDate": "2013-02-25"
                    }
                },
                {
                    "description": "",
                    "label": "carolina_poll_fall93_xtabs.pdf",
                    "restricted": false,
                    "version": 1,
                    "datasetVersionId": 3614,
                    "categories": [
                        "Cross-Tabulations, PDF File"
                    ],
                    "dataFile": {
                        "id": 16666,
                        "persistentId": "",
                        "pidURL": "",
                        "filename": "carolina_poll_fall93_xtabs.pdf",
                        "contentType": "application/pdf",
                        "filesize": 3041284,
                        "description": "",
                        "storageIdentifier": "carolina_poll_fall93_xtabs.pdf",
                        "rootDataFileId": -1,
                        "md5": "",
                        "checksum": {
                            "type": "MD5",
                            "value": ""
                        },
                        "creationDate": "2013-02-25"
                    }
                }
            ]
        }
    }
}